pineline/__init__.py
pineline-0.2.4.dist-info/METADATA
pineline-0.2.4.dist-info/WHEEL
pineline-0.2.4.dist-info/RECORD
