Metadata-Version: 2.1
Name: pineline
Version: 0.2.4
Summary: Theory predictions for PDF fitting
Author: Andrea Barontini
Author-email: andrea.barontini@mi.infn.it
Requires-Python: >=3.8,<3.12
Classifier: Programming Language :: Python :: 3
Classifier: Programming Language :: Python :: 3.8
Classifier: Programming Language :: Python :: 3.9
Classifier: Programming Language :: Python :: 3.10
Classifier: Programming Language :: Python :: 3.11
Provides-Extra: full
Requires-Dist: eko (>=0.14.0,<0.15.0)
Requires-Dist: pineappl (>=0.6.2,<0.7.0)
Requires-Dist: pinefarm (==0.3.2) ; extra == "full"
Requires-Dist: pineko (>=0.4.5,<0.5.0)
